[{"name":"Nikola Jokic","rank":"15","pos":"PF/C","team":"DEN","gp":"75","mpg":"30","pts":"17.2","reb":"10.3","ast":"5","stl":"1","blk":"0.8","m3s":"1.3","fgma":"6.5/11.8","fg":"0.55","ftma":"2.9/3.6","ft":"0.82","to":"2.4","id":114},{"name":"Chris Paul","rank":"12","pos":"PG","team":"HOU","gp":"72","mpg":"31","pts":"18.6","reb":"4.7","ast":"9.4","stl":"1.8","blk":"0.2","m3s":"2","fgma":"6.5/13.9","fg":"0.47","ftma":"3.6/4.0","ft":"0.9","to":"2.4","id":111},{"name":"Bradley Beal","rank":"33","pos":"SG","team":"WAS","gp":"71","mpg":"34.5","pts":"21.6","reb":"3.6","ast":"3.4","stl":"1","blk":"0.3","m3s":"2.6","fgma":"7.7/16.4","fg":"0.47","ftma":"3.5/4.3","ft":"0.82","to":"2","id":132},{"name":"Paul Millsap","rank":"25","pos":"PF/C","team":"DEN","gp":"74","mpg":"31","pts":"15.9","reb":"7.5","ast":"3.2","stl":"1.4","blk":"1.1","m3s":"1.7","fgma":"5.3/11.7","fg":"0.45","ftma":"3.6/4.7","ft":"0.76","to":"2","id":124},{"name":"Nicolas Batum","rank":"51","pos":"SG/SF","team":"CHA","gp":"72","mpg":"33.5","pts":"13.6","reb":"6.1","ast":"5.6","stl":"1","blk":"0.5","m3s":"2","fgma":"4.7/11.7","fg":"0.4","ftma":"2.3/2.7","ft":"0.84","to":"2.4","id":150},{"name":"LaMarcus Aldridge","rank":"53","pos":"PF/C","team":"SAS","gp":"72","mpg":"32.5","pts":"17.3","reb":"7.9","ast":"1.8","stl":"0.6","blk":"1.1","m3s":"0.3","fgma":"7.0/14.7","fg":"0.48","ftma":"3.0/3.6","ft":"0.82","to":"1.3","id":152},{"name":"George Hill","rank":"83","pos":"PG/SG","team":"SAC","gp":"62","mpg":"31","pts":"13.6","reb":"3.7","ast":"3.9","stl":"1","blk":"0.3","m3s":"1.7","fgma":"4.8/10.9","fg":"0.44","ftma":"2.2/2.8","ft":"0.78","to":"1.5","id":182},{"name":"Jamal Murray","rank":"115","pos":"PG/SG","team":"DEN","gp":"78","mpg":"28","pts":"13.2","reb":"3.4","ast":"2.6","stl":"0.9","blk":"0.4","m3s":"1.9","fgma":"4.8/11.7","fg":"0.41","ftma":"1.8/2.1","ft":"0.88","to":"1.7","id":214},{"name":"Markieff Morris","rank":"64","pos":"SF/PF","team":"WAS","gp":"74","mpg":"31","pts":"14.1","reb":"6.4","ast":"1.9","stl":"1.1","blk":"0.6","m3s":"1.1","fgma":"5.4/12.0","fg":"0.45","ftma":"2.2/2.8","ft":"0.8","to":"2","id":163},{"name":"Derrick Favors","rank":"87","pos":"PF/C","team":"UTA","gp":"65","mpg":"27","pts":"12.4","reb":"7.2","ast":"1.3","stl":"0.8","blk":"1.1","m3s":"0","fgma":"5.1/10.1","fg":"0.51","ftma":"2.1/3.1","ft":"0.69","to":"1.4","id":186},{"name":"Taurean Prince","rank":"104","pos":"SF","team":"ATL","gp":"67","mpg":"28","pts":"9.9","reb":"4.8","ast":"1.7","stl":"1.2","blk":"0.8","m3s":"1.1","fgma":"3.3/8.0","fg":"0.41","ftma":"2.1/2.7","ft":"0.8","to":"1.6","id":203},{"name":"Marcus Smart","rank":"113","pos":"PG","team":"BOS","gp":"74","mpg":"28","pts":"10.4","reb":"3.6","ast":"4","stl":"1.2","blk":"0.4","m3s":"1.4","fgma":"3.3/8.8","fg":"0.38","ftma":"2.4/3.0","ft":"0.78","to":"1.5","id":212},{"name":"Rondae Hollis-Jefferson","rank":"69","pos":"SF/PF","team":"BKN","gp":"75","mpg":"26","pts":"9.9","reb":"6.8","ast":"2.2","stl":"1.4","blk":"0.7","m3s":"0.3","fgma":"3.5/7.6","fg":"0.46","ftma":"2.5/3.3","ft":"0.78","to":"1.5","id":168}]